np_aind_metadata/__init__.py
np_aind_metadata/common.py
np_aind_metadata/np.py
np_aind_metadata/py.typed
np_aind_metadata/rigs.py
np_aind_metadata/storage.py
np_aind_metadata/update.py
np_aind_metadata/utils.py
np_aind_metadata/etls/__init__.py
np_aind_metadata/etls/dynamic_routing_task_etl.py
np_aind_metadata/init/__init__.py
np_aind_metadata/init/behavior_box.py
np_aind_metadata/init/neuropixels_rig.py
np_aind_metadata/integrations/__init__.py
np_aind_metadata/integrations/dynamic_routing_task.py
np_aind_metadata/scripts/main.py
np_aind_metadata-0.1.18.dist-info/LICENSE
np_aind_metadata-0.1.18.dist-info/METADATA
np_aind_metadata-0.1.18.dist-info/WHEEL
np_aind_metadata-0.1.18.dist-info/entry_points.txt
np_aind_metadata-0.1.18.dist-info/top_level.txt
np_aind_metadata-0.1.18.dist-info/RECORD
