Metadata-Version: 2.1
Name: np-aind-metadata
Version: 0.1.18
Author-email: Christopher Mochizuki <chrism@alleninstitute.org>
License: MIT
Project-URL: Repository, https://github.com/AllenInstitute/np-aind-metadata
Project-URL: Issues, https://github.com/AllenInstitute/np-aind-metadata/issues
Classifier: Development Status :: 3 - Alpha
Classifier: Programming Language :: Python :: 3
Classifier: Programming Language :: Python :: 3.9
Classifier: Programming Language :: Python :: 3.10
Classifier: Programming Language :: Python :: 3.11
Classifier: License :: OSI Approved :: MIT License
Classifier: Operating System :: Microsoft :: Windows
Classifier: Operating System :: POSIX :: Linux
Requires-Python: >=3.10
License-File: LICENSE
Requires-Dist: h5py>=3.10.0
Requires-Dist: pyyaml>=6.0.1
Requires-Dist: np-session>=0.6.40
Requires-Dist: np-config>=0.4.27
Requires-Dist: aind-metadata-mapper==0.18.2
Requires-Dist: aind-data-schema==1.1.1
Provides-Extra: np
Requires-Dist: np-config>=0.4.27; extra == "np"
